bumblebee/__init__.py
bumblebee/bases/__init__.py
bumblebee/bases/constants.py
bumblebee/bases/Dataset.py
bumblebee/bases/Effect.py
bumblebee/bases/IManager.py
bumblebee/bases/Source.py
bumblebee/datasets/__init__.py
bumblebee/datasets/batch/__init__.py
bumblebee/datasets/batch/Batch.py
bumblebee/datasets/batch/NumpyBatch.py
bumblebee/datasets/batch/TorchBatch.py
bumblebee/datasets/NLimiter.py
bumblebee/datasets/Single.py
bumblebee/effects/__init__.py
bumblebee/effects/CurrentFrame.py
bumblebee/effects/End.py
bumblebee/effects/FrameSkip.py
bumblebee/effects/GoTo.py
bumblebee/effects/LimitedRead.py
bumblebee/effects/Loop.py
bumblebee/effects/RandomSeek.py
bumblebee/effects/Start.py
bumblebee/managers/__init__.py
bumblebee/managers/BinaryClassification.py
bumblebee/misc/__init__.py
bumblebee/misc/WindowStream.py
bumblebee/sources/__init__.py
bumblebee/sources/DeviceStream.py
bumblebee/sources/FileStream.py
bumblebee/sources/WebStream.py
eyecu_bumblebee-0.5.7.dist-info/entry_points.txt
eyecu_bumblebee-0.5.7.dist-info/LICENSE
eyecu_bumblebee-0.5.7.dist-info/WHEEL
eyecu_bumblebee-0.5.7.dist-info/METADATA
eyecu_bumblebee-0.5.7.dist-info/RECORD
